lib_test_package/__init__.py
lib_test_package/main.py
lib_test_package-1.0.4.dist-info/METADATA
lib_test_package-1.0.4.dist-info/WHEEL
lib_test_package-1.0.4.dist-info/top_level.txt
lib_test_package-1.0.4.dist-info/RECORD
