Metadata-Version: 2.4
Name: lib-test-package
Version: 1.0.4
Summary: This package is useless
Author-email: Python anonym <info@realpython.com>
Keywords: test
Classifier: License :: OSI Approved :: MIT License
Classifier: Programming Language :: Python
Classifier: Programming Language :: Python :: 3
Requires-Python: >=3.12
Requires-Dist: pandas>=2.2.0
